{
  "Benevento": {
    "first_seen_utc": "20260220T165619Z",
    "last_seen_utc": "20260220T190329Z",
    "seen_count": 6
  },
  "Roma Termini": {
    "first_seen_utc": "20260220T165619Z",
    "last_seen_utc": "20260220T190329Z",
    "seen_count": 6
  },
  "Trieste C.le": {
    "first_seen_utc": "20260220T165619Z",
    "last_seen_utc": "20260220T190329Z",
    "seen_count": 6
  },
  "S.Donà-Jesolo": {
    "first_seen_utc": "20260220T165619Z",
    "last_seen_utc": "20260220T190329Z",
    "seen_count": 6
  },
  "Ferrara": {
    "first_seen_utc": "20260220T165619Z",
    "last_seen_utc": "20260220T190329Z",
    "seen_count": 6
  },
  "Napoli Afragola": {
    "first_seen_utc": "20260220T165619Z",
    "last_seen_utc": "20260220T190329Z",
    "seen_count": 6
  },
  "Monfalcone": {
    "first_seen_utc": "20260220T165619Z",
    "last_seen_utc": "20260220T190329Z",
    "seen_count": 6
  },
  "Conegliano": {
    "first_seen_utc": "20260220T165619Z",
    "last_seen_utc": "20260220T190329Z",
    "seen_count": 6
  },
  "Napoli": {
    "first_seen_utc": "20260220T165619Z",
    "last_seen_utc": "20260220T190329Z",
    "seen_count": 6
  },
  "Molfetta": {
    "first_seen_utc": "20260220T165619Z",
    "last_seen_utc": "20260220T190329Z",
    "seen_count": 6
  },
  "Mediopadana R.Emilia": {
    "first_seen_utc": "20260220T165619Z",
    "last_seen_utc": "20260220T190329Z",
    "seen_count": 6
  },
  "Milano Expo Rho": {
    "first_seen_utc": "20260220T165619Z",
    "last_seen_utc": "20260220T190329Z",
    "seen_count": 6
  },
  "Trani": {
    "first_seen_utc": "20260220T165619Z",
    "last_seen_utc": "20260220T190329Z",
    "seen_count": 6
  },
  "Peschiera": {
    "first_seen_utc": "20260220T165619Z",
    "last_seen_utc": "20260220T190329Z",
    "seen_count": 6
  },
  "Treviso C.le": {
    "first_seen_utc": "20260220T165619Z",
    "last_seen_utc": "20260220T190329Z",
    "seen_count": 6
  },
  "Trieste Airport": {
    "first_seen_utc": "20260220T165619Z",
    "last_seen_utc": "20260220T190329Z",
    "seen_count": 6
  },
  "Genova Brignole": {
    "first_seen_utc": "20260220T165619Z",
    "last_seen_utc": "20260220T190329Z",
    "seen_count": 6
  },
  "Venezia Mestre": {
    "first_seen_utc": "20260220T165619Z",
    "last_seen_utc": "20260220T190329Z",
    "seen_count": 6
  },
  "Barletta": {
    "first_seen_utc": "20260220T165619Z",
    "last_seen_utc": "20260220T190329Z",
    "seen_count": 6
  },
  "Firenze Santa Maria Novella": {
    "first_seen_utc": "20260220T165619Z",
    "last_seen_utc": "20260220T190329Z",
    "seen_count": 6
  },
  "Bologna centrale": {
    "first_seen_utc": "20260220T165619Z",
    "last_seen_utc": "20260220T190329Z",
    "seen_count": 6
  },
  "Milano Rogoredo": {
    "first_seen_utc": "20260220T165619Z",
    "last_seen_utc": "20260220T190329Z",
    "seen_count": 6
  },
  "Torino Porta di Susa": {
    "first_seen_utc": "20260220T165619Z",
    "last_seen_utc": "20260220T190329Z",
    "seen_count": 6
  },
  "Salerno": {
    "first_seen_utc": "20260220T165619Z",
    "last_seen_utc": "20260220T190329Z",
    "seen_count": 6
  },
  "Milano Centrale": {
    "first_seen_utc": "20260220T165619Z",
    "last_seen_utc": "20260220T190329Z",
    "seen_count": 6
  },
  "Foggia": {
    "first_seen_utc": "20260220T165619Z",
    "last_seen_utc": "20260220T190329Z",
    "seen_count": 6
  },
  "Brescia": {
    "first_seen_utc": "20260220T165619Z",
    "last_seen_utc": "20260220T190329Z",
    "seen_count": 6
  },
  "Desenzano": {
    "first_seen_utc": "20260220T165619Z",
    "last_seen_utc": "20260220T190329Z",
    "seen_count": 6
  },
  "Roma Tiburtina": {
    "first_seen_utc": "20260220T165619Z",
    "last_seen_utc": "20260220T190329Z",
    "seen_count": 6
  },
  "Portogruaro": {
    "first_seen_utc": "20260220T165619Z",
    "last_seen_utc": "20260220T190329Z",
    "seen_count": 6
  },
  "Pordenone": {
    "first_seen_utc": "20260220T165619Z",
    "last_seen_utc": "20260220T190329Z",
    "seen_count": 6
  },
  "Udine": {
    "first_seen_utc": "20260220T165619Z",
    "last_seen_utc": "20260220T190329Z",
    "seen_count": 6
  },
  "Genova Piazza Principe": {
    "first_seen_utc": "20260220T165619Z",
    "last_seen_utc": "20260220T190329Z",
    "seen_count": 6
  },
  "Vicenza": {
    "first_seen_utc": "20260220T165619Z",
    "last_seen_utc": "20260220T190329Z",
    "seen_count": 6
  },
  "Verona Porta Nuova": {
    "first_seen_utc": "20260220T165619Z",
    "last_seen_utc": "20260220T190329Z",
    "seen_count": 6
  },
  "Torino Porta Nuova": {
    "first_seen_utc": "20260220T165619Z",
    "last_seen_utc": "20260220T190329Z",
    "seen_count": 6
  },
  "Caserta": {
    "first_seen_utc": "20260220T165619Z",
    "last_seen_utc": "20260220T190329Z",
    "seen_count": 6
  },
  "Bisceglie": {
    "first_seen_utc": "20260220T165619Z",
    "last_seen_utc": "20260220T190329Z",
    "seen_count": 6
  },
  "Padova": {
    "first_seen_utc": "20260220T165619Z",
    "last_seen_utc": "20260220T190329Z",
    "seen_count": 6
  },
  "Latisana-Lignano": {
    "first_seen_utc": "20260220T165619Z",
    "last_seen_utc": "20260220T190329Z",
    "seen_count": 6
  },
  "Bari Centrale": {
    "first_seen_utc": "20260220T165619Z",
    "last_seen_utc": "20260220T190329Z",
    "seen_count": 6
  },
  "Venezia Santa Lucia": {
    "first_seen_utc": "20260220T165619Z",
    "last_seen_utc": "20260220T190329Z",
    "seen_count": 6
  },
  "Trento": {
    "first_seen_utc": "20260220T172318Z",
    "last_seen_utc": "20260220T190329Z",
    "seen_count": 4
  },
  "Bolzano": {
    "first_seen_utc": "20260220T172318Z",
    "last_seen_utc": "20260220T190329Z",
    "seen_count": 4
  },
  "Rovereto": {
    "first_seen_utc": "20260220T172318Z",
    "last_seen_utc": "20260220T190329Z",
    "seen_count": 4
  }
}